dircap/__init__.py
dircap/cli.py
dircap/config.py
dircap/format.py
dircap/scan.py
dircap-0.1.0.dist-info/licenses/LICENSE
tests/test_bytes_basic.py
tests/test_config_actions.py
tests/test_evaluate.py
tests/test_format.py
dircap-0.1.0.dist-info/METADATA
dircap-0.1.0.dist-info/WHEEL
dircap-0.1.0.dist-info/entry_points.txt
dircap-0.1.0.dist-info/top_level.txt
dircap-0.1.0.dist-info/RECORD
