Metadata-Version: 2.4
Name: dircap
Version: 0.1.0
Summary: Set folder size caps and get warned when you exceed them.
Author: Varun Singh
License: MIT
Keywords: disk,quota,folder,cli,storage
Requires-Python: >=3.10
License-File: LICENSE
Requires-Dist: typer>=0.21.1
Requires-Dist: rich>=14.2.0
Requires-Dist: tomli>=2.4.0; python_version < "3.11"
Provides-Extra: dev
Requires-Dist: pytest>=9.0.2; extra == "dev"
Requires-Dist: ruff>=0.14.13; extra == "dev"
Dynamic: license-file
